recommend/__init__.py
recommend/main.py
recommend/utils.py
recommend-0.2.1.dist-info/LICENSE
recommend-0.2.1.dist-info/METADATA
recommend-0.2.1.dist-info/WHEEL
recommend-0.2.1.dist-info/top_level.txt
recommend-0.2.1.dist-info/RECORD
