Metadata-Version: 2.1
Name: recommend
Version: 0.2.1
Summary: Implicit Recommender
Home-page: https://github.com/maxhumber/recommend
Author: Max Humber
Author-email: max.humber@gmail.com
License: MIT
Keywords: recommend
Platform: UNKNOWN
Classifier: License :: OSI Approved :: MIT License
Classifier: Programming Language :: Python :: 3.6
Requires-Python: >=3.6
Requires-Dist: scipy
Requires-Dist: numpy
